__init__.py
NeoPortfolio/BtEngine.py
NeoPortfolio/BtResult.py
NeoPortfolio/BtStateRecord.py
NeoPortfolio/BtStrategy.py
NeoPortfolio/Cache.py
NeoPortfolio/CacheConstructor.py
NeoPortfolio/CustomTypes.py
NeoPortfolio/INDEX_MAP.json
NeoPortfolio/Markowitz.py
NeoPortfolio/Portfolio.py
NeoPortfolio/ReturnPred.py
NeoPortfolio/Sentiment.py
NeoPortfolio/__init__.py
NeoPortfolio/nCrEngine.py
NeoPortfolio/nCrOptimize.py
NeoPortfolio/nCrResult.py
NeoPortfolio-1.3.3.dist-info/LICENSE
NeoPortfolio-1.3.3.dist-info/METADATA
NeoPortfolio-1.3.3.dist-info/WHEEL
NeoPortfolio-1.3.3.dist-info/top_level.txt
NeoPortfolio-1.3.3.dist-info/RECORD
