Metadata-Version: 2.2
Name: NeoPortfolio
Version: 1.3.3
Summary: Portfolio Selection, Optimization, and backtesting library with sentiment analysis and ML features
Author-email: Ege Güney Kıymaç <guneykiymac@gmail.com>, Cem Köymen <cemkoymen5@gmail.com>
License:                     GNU GENERAL PUBLIC LICENSE
Project-URL: homepage, https://github.com/GongJr0/NeoPortfolio
Project-URL: documentation, https://gongjr0.github.io/NeoPortfolio
License-File: LICENSE
Requires-Dist: beautifulsoup4>=4.11.2
Requires-Dist: ipython>=8.14.0
Requires-Dist: matplotlib>=3.7.1
Requires-Dist: newsapi-python>=0.2.7
Requires-Dist: numpy>=1.24.3
Requires-Dist: pandas>=2.0.2
Requires-Dist: plotly>=5.24.1
Requires-Dist: python-dotenv>=1.0.1
Requires-Dist: requests>=2.32.3
Requires-Dist: requests-cache>=1.2.1
Requires-Dist: scikit_learn>=1.2.2
Requires-Dist: scipy>=1.15.0
Requires-Dist: torch>=2.5.1
Requires-Dist: tqdm>=4.65.0
Requires-Dist: transformers>=4.47.1
Requires-Dist: yfinance>=0.2.33
